{
  "builds": [
    {
      "build": "https://ci.chromium.org/b/8914374329399439616",
      "duration": "4 mins",
      "info": "",
      "result": "Success",
      "time": "Saturday, 04-May-19 16:30:34 UTC"
    },
    {
      "build": "https://ci.chromium.org/b/8914374660740614704",
      "duration": "3 mins 58 secs",
      "info": "",
      "result": "Success",
      "time": "Saturday, 04-May-19 16:25:12 UTC"
    },
    {
      "build": "https://ci.chromium.org/b/8914375017222023664",
      "duration": "3 mins 56 secs",
      "info": "",
      "result": "Success",
      "time": "Saturday, 04-May-19 16:19:54 UTC"
    },
    {
      "build": "https://ci.chromium.org/b/8914375358901782544",
      "duration": "4 mins 3 secs",
      "info": "",
      "result": "Success",
      "time": "Saturday, 04-May-19 16:14:16 UTC"
    },
    {
      "build": "https://ci.chromium.org/b/8914375696803291504",
      "duration": "3 mins 57 secs",
      "info": "",
      "result": "Success",
      "time": "Saturday, 04-May-19 16:08:48 UTC"
    },
    {
      "build": "https://ci.chromium.org/b/8914376042522956320",
      "duration": "4 mins 3 secs",
      "info": "",
      "result": "Success",
      "time": "Saturday, 04-May-19 16:03:27 UTC"
    },
    {
      "build": "https://ci.chromium.org/b/8914376373862489856",
      "duration": "3 mins 55 secs",
      "info": "",
      "result": "Success",
      "time": "Saturday, 04-May-19 15:57:56 UTC"
    },
    {
      "build": "https://ci.chromium.org/b/8914376720042101760",
      "duration": "4 mins 1 secs",
      "info": "",
      "result": "Success",
      "time": "Saturday, 04-May-19 15:52:40 UTC"
    },
    {
      "build": "https://ci.chromium.org/b/8914377057779844304",
      "duration": "4 mins",
      "info": "",
      "result": "Success",
      "time": "Saturday, 04-May-19 15:47:11 UTC"
    },
    {
      "build": "https://ci.chromium.org/b/8914377401503330368",
      "duration": "3 mins 53 secs",
      "info": "",
      "result": "Success",
      "time": "Saturday, 04-May-19 15:41:50 UTC"
    },
    {
      "build": "https://ci.chromium.org/b/8914377762327925664",
      "duration": "3 mins 59 secs",
      "info": "",
      "result": "Success",
      "time": "Saturday, 04-May-19 15:36:20 UTC"
    },
    {
      "build": "https://ci.chromium.org/b/8914378108138424304",
      "duration": "4 mins 1 secs",
      "info": "",
      "result": "Success",
      "time": "Saturday, 04-May-19 15:30:37 UTC"
    },
    {
      "build": "https://ci.chromium.org/b/8914378454399676080",
      "duration": "3 mins 59 secs",
      "info": "",
      "result": "Success",
      "time": "Saturday, 04-May-19 15:25:07 UTC"
    },
    {
      "build": "https://ci.chromium.org/b/8914378808501643440",
      "duration": "4 mins 10 secs",
      "info": "",
      "result": "Success",
      "time": "Saturday, 04-May-19 15:19:36 UTC"
    },
    {
      "build": "https://ci.chromium.org/b/8914379144146207616",
      "duration": "3 mins 55 secs",
      "info": "",
      "result": "Success",
      "time": "Saturday, 04-May-19 15:14:00 UTC"
    },
    {
      "build": "https://ci.chromium.org/b/8914379494712957712",
      "duration": "4 mins 9 secs",
      "info": "",
      "result": "Success",
      "time": "Saturday, 04-May-19 15:08:38 UTC"
    },
    {
      "build": "https://ci.chromium.org/b/8914379838705607408",
      "duration": "3 mins 59 secs",
      "info": "",
      "result": "Success",
      "time": "Saturday, 04-May-19 15:03:02 UTC"
    },
    {
      "build": "https://ci.chromium.org/b/8914380177812631152",
      "duration": "4 mins 1 secs",
      "info": "",
      "result": "Success",
      "time": "Saturday, 04-May-19 14:57:38 UTC"
    },
    {
      "build": "https://ci.chromium.org/b/8914380513739543264",
      "duration": "3 mins 57 secs",
      "info": "",
      "result": "Success",
      "time": "Saturday, 04-May-19 14:52:10 UTC"
    },
    {
      "build": "https://ci.chromium.org/b/8914380874219937648",
      "duration": "4 mins 23 secs",
      "info": "",
      "result": "Success",
      "time": "Saturday, 04-May-19 14:46:52 UTC"
    },
    {
      "build": "https://ci.chromium.org/b/8914381226734798016",
      "duration": "4 mins 10 secs",
      "info": "",
      "result": "Success",
      "time": "Saturday, 04-May-19 14:41:08 UTC"
    },
    {
      "build": "https://ci.chromium.org/b/8914381556314870144",
      "duration": "3 mins 59 secs",
      "info": "",
      "result": "Success",
      "time": "Saturday, 04-May-19 14:35:34 UTC"
    },
    {
      "build": "https://ci.chromium.org/b/8914381889560419648",
      "duration": "3 mins 55 secs",
      "info": "",
      "result": "Success",
      "time": "Saturday, 04-May-19 14:30:19 UTC"
    },
    {
      "build": "https://ci.chromium.org/b/8914382218557021920",
      "duration": "3 mins 54 secs",
      "info": "",
      "result": "Success",
      "time": "Saturday, 04-May-19 14:25:01 UTC"
    },
    {
      "build": "https://ci.chromium.org/b/8914382556447769568",
      "duration": "3 mins 54 secs",
      "info": "",
      "result": "Success",
      "time": "Saturday, 04-May-19 14:19:48 UTC"
    },
    {
      "build": "https://ci.chromium.org/b/8914382896271491632",
      "duration": "3 mins 56 secs",
      "info": "",
      "result": "Success",
      "time": "Saturday, 04-May-19 14:14:26 UTC"
    },
    {
      "build": "https://ci.chromium.org/b/8914383246489831040",
      "duration": "4 mins 9 secs",
      "info": "",
      "result": "Success",
      "time": "Saturday, 04-May-19 14:09:01 UTC"
    },
    {
      "build": "https://ci.chromium.org/b/8914383587963291952",
      "duration": "4 mins",
      "info": "",
      "result": "Success",
      "time": "Saturday, 04-May-19 14:03:22 UTC"
    },
    {
      "build": "https://ci.chromium.org/b/8914383934363260544",
      "duration": "4 mins 3 secs",
      "info": "",
      "result": "Success",
      "time": "Saturday, 04-May-19 13:58:01 UTC"
    },
    {
      "build": "https://ci.chromium.org/b/8914384294675710480",
      "duration": "4 mins 27 secs",
      "info": "",
      "result": "Success",
      "time": "Saturday, 04-May-19 13:52:31 UTC"
    },
    {
      "build": "https://ci.chromium.org/b/8914384636939612000",
      "duration": "4 mins 4 secs",
      "info": "",
      "result": "Success",
      "time": "Saturday, 04-May-19 13:46:44 UTC"
    },
    {
      "build": "https://ci.chromium.org/b/8914384966012009872",
      "duration": "3 mins 55 secs",
      "info": "",
      "result": "Success",
      "time": "Saturday, 04-May-19 13:41:20 UTC"
    },
    {
      "build": "https://ci.chromium.org/b/8914385316123002768",
      "duration": "4 mins 3 secs",
      "info": "",
      "result": "Success",
      "time": "Saturday, 04-May-19 13:35:59 UTC"
    },
    {
      "build": "https://ci.chromium.org/b/8914385653448571600",
      "duration": "3 mins 57 secs",
      "info": "",
      "result": "Success",
      "time": "Saturday, 04-May-19 13:30:32 UTC"
    },
    {
      "build": "https://ci.chromium.org/b/8914385998085800624",
      "duration": "4 mins 3 secs",
      "info": "",
      "result": "Success",
      "time": "Saturday, 04-May-19 13:25:11 UTC"
    },
    {
      "build": "https://ci.chromium.org/b/8914386328823539360",
      "duration": "3 mins 56 secs",
      "info": "",
      "result": "Success",
      "time": "Saturday, 04-May-19 13:19:43 UTC"
    },
    {
      "build": "https://ci.chromium.org/b/8914386727854302896",
      "duration": "3 mins 57 secs",
      "info": "",
      "result": "Success",
      "time": "Saturday, 04-May-19 13:14:27 UTC"
    },
    {
      "build": "https://ci.chromium.org/b/8914387075655303824",
      "duration": "4 mins 8 secs",
      "info": "",
      "result": "Success",
      "time": "Saturday, 04-May-19 13:08:07 UTC"
    },
    {
      "build": "https://ci.chromium.org/b/8914387421923827312",
      "duration": "4 mins 5 secs",
      "info": "",
      "result": "Success",
      "time": "Saturday, 04-May-19 13:02:36 UTC"
    },
    {
      "build": "https://ci.chromium.org/b/8914387782687438112",
      "duration": "3 mins 56 secs",
      "info": "",
      "result": "Success",
      "time": "Saturday, 04-May-19 12:57:04 UTC"
    },
    {
      "build": "https://ci.chromium.org/b/8914388121953524592",
      "duration": "3 mins 55 secs",
      "info": "",
      "result": "Success",
      "time": "Saturday, 04-May-19 12:51:19 UTC"
    },
    {
      "build": "https://ci.chromium.org/b/8914388459960497696",
      "duration": "4 mins",
      "info": "",
      "result": "Success",
      "time": "Saturday, 04-May-19 12:45:56 UTC"
    },
    {
      "build": "https://ci.chromium.org/b/8914388797465985072",
      "duration": "4 mins 1 secs",
      "info": "",
      "result": "Success",
      "time": "Saturday, 04-May-19 12:40:36 UTC"
    },
    {
      "build": "https://ci.chromium.org/b/8914389139574830160",
      "duration": "4 mins 1 secs",
      "info": "",
      "result": "Success",
      "time": "Saturday, 04-May-19 12:35:09 UTC"
    },
    {
      "build": "https://ci.chromium.org/b/8914389468446215296",
      "duration": "3 mins 55 secs",
      "info": "",
      "result": "Success",
      "time": "Saturday, 04-May-19 12:29:48 UTC"
    },
    {
      "build": "https://ci.chromium.org/b/8914389810280267424",
      "duration": "3 mins 57 secs",
      "info": "",
      "result": "Success",
      "time": "Saturday, 04-May-19 12:24:33 UTC"
    },
    {
      "build": "https://ci.chromium.org/b/8914390139800255248",
      "duration": "4 mins 1 secs",
      "info": "",
      "result": "Success",
      "time": "Saturday, 04-May-19 12:19:07 UTC"
    },
    {
      "build": "https://ci.chromium.org/b/8914390464668711104",
      "duration": "3 mins 55 secs",
      "info": "",
      "result": "Success",
      "time": "Saturday, 04-May-19 12:13:53 UTC"
    },
    {
      "build": "https://ci.chromium.org/b/8914390831621814432",
      "duration": "4 mins 21 secs",
      "info": "",
      "result": "Success",
      "time": "Saturday, 04-May-19 12:08:41 UTC"
    },
    {
      "build": "https://ci.chromium.org/b/8914391173653890128",
      "duration": "4 mins 2 secs",
      "info": "",
      "result": "Success",
      "time": "Saturday, 04-May-19 12:02:52 UTC"
    },
    {
      "build": "https://ci.chromium.org/b/8914391504930571344",
      "duration": "4 mins",
      "info": "",
      "result": "Success",
      "time": "Saturday, 04-May-19 11:57:27 UTC"
    },
    {
      "build": "https://ci.chromium.org/b/8914391838329582272",
      "duration": "3 mins 56 secs",
      "info": "",
      "result": "Success",
      "time": "Saturday, 04-May-19 11:52:09 UTC"
    },
    {
      "build": "https://ci.chromium.org/b/8914392174057873232",
      "duration": "3 mins 56 secs",
      "info": "",
      "result": "Success",
      "time": "Saturday, 04-May-19 11:46:54 UTC"
    },
    {
      "build": "https://ci.chromium.org/b/8914392513926508944",
      "duration": "4 mins 1 secs",
      "info": "",
      "result": "Success",
      "time": "Saturday, 04-May-19 11:41:32 UTC"
    },
    {
      "build": "https://ci.chromium.org/b/8914392840344763792",
      "duration": "3 mins 57 secs",
      "info": "",
      "result": "Success",
      "time": "Saturday, 04-May-19 11:36:09 UTC"
    },
    {
      "build": "https://ci.chromium.org/b/8914393180635503424",
      "duration": "4 mins 1 secs",
      "info": "",
      "result": "Success",
      "time": "Saturday, 04-May-19 11:30:57 UTC"
    },
    {
      "build": "https://ci.chromium.org/b/8914393526651653024",
      "duration": "4 mins 6 secs",
      "info": "",
      "result": "Success",
      "time": "Saturday, 04-May-19 11:25:29 UTC"
    },
    {
      "build": "https://ci.chromium.org/b/8914393868422899840",
      "duration": "4 mins",
      "info": "",
      "result": "Success",
      "time": "Saturday, 04-May-19 11:20:02 UTC"
    },
    {
      "build": "https://ci.chromium.org/b/8914394199908244112",
      "duration": "3 mins 54 secs",
      "info": "",
      "result": "Success",
      "time": "Saturday, 04-May-19 11:14:38 UTC"
    },
    {
      "build": "https://ci.chromium.org/b/8914394547902105840",
      "duration": "4 mins 10 secs",
      "info": "",
      "result": "Success",
      "time": "Saturday, 04-May-19 11:09:21 UTC"
    },
    {
      "build": "https://ci.chromium.org/b/8914394885580832928",
      "duration": "3 mins 58 secs",
      "info": "",
      "result": "Success",
      "time": "Saturday, 04-May-19 11:03:50 UTC"
    },
    {
      "build": "https://ci.chromium.org/b/8914395233512924768",
      "duration": "4 mins 5 secs",
      "info": "",
      "result": "Success",
      "time": "Saturday, 04-May-19 10:58:26 UTC"
    },
    {
      "build": "https://ci.chromium.org/b/8914395571404674128",
      "duration": "4 mins 2 secs",
      "info": "",
      "result": "Success",
      "time": "Saturday, 04-May-19 10:52:54 UTC"
    },
    {
      "build": "https://ci.chromium.org/b/8914395952546988112",
      "duration": "4 mins 42 secs",
      "info": "",
      "result": "Success",
      "time": "Saturday, 04-May-19 10:47:32 UTC"
    },
    {
      "build": "https://ci.chromium.org/b/8914396286716482544",
      "duration": "3 mins 59 secs",
      "info": "",
      "result": "Success",
      "time": "Saturday, 04-May-19 10:41:29 UTC"
    },
    {
      "build": "https://ci.chromium.org/b/8914397024890855664",
      "duration": "4 mins 1 secs",
      "info": "",
      "result": "Success",
      "time": "Saturday, 04-May-19 10:36:08 UTC"
    },
    {
      "build": "https://ci.chromium.org/b/8914397370748206864",
      "duration": "4 mins 3 secs",
      "info": "",
      "result": "Success",
      "time": "Saturday, 04-May-19 10:24:27 UTC"
    },
    {
      "build": "https://ci.chromium.org/b/8914397702145226896",
      "duration": "4 mins",
      "info": "",
      "result": "Success",
      "time": "Saturday, 04-May-19 10:18:57 UTC"
    },
    {
      "build": "https://ci.chromium.org/b/8914398041948194592",
      "duration": "4 mins 4 secs",
      "info": "",
      "result": "Success",
      "time": "Saturday, 04-May-19 10:13:40 UTC"
    },
    {
      "build": "https://ci.chromium.org/b/8914398391959116432",
      "duration": "4 mins 4 secs",
      "info": "",
      "result": "Success",
      "time": "Saturday, 04-May-19 10:08:16 UTC"
    },
    {
      "build": "https://ci.chromium.org/b/8914398729846919232",
      "duration": "4 mins 5 secs",
      "info": "",
      "result": "Success",
      "time": "Saturday, 04-May-19 10:02:43 UTC"
    },
    {
      "build": "https://ci.chromium.org/b/8914399075612319904",
      "duration": "3 mins 59 secs",
      "info": "",
      "result": "Success",
      "time": "Saturday, 04-May-19 09:57:18 UTC"
    },
    {
      "build": "https://ci.chromium.org/b/8914399419860380592",
      "duration": "3 mins 57 secs",
      "info": "",
      "result": "Success",
      "time": "Saturday, 04-May-19 09:51:49 UTC"
    },
    {
      "build": "https://ci.chromium.org/b/8914399755401069408",
      "duration": "4 mins 5 secs",
      "info": "",
      "result": "Success",
      "time": "Saturday, 04-May-19 09:46:23 UTC"
    },
    {
      "build": "https://ci.chromium.org/b/8914400107695376320",
      "duration": "4 mins 3 secs",
      "info": "",
      "result": "Success",
      "time": "Saturday, 04-May-19 09:41:02 UTC"
    },
    {
      "build": "https://ci.chromium.org/b/8914400482423068592",
      "duration": "4 mins 25 secs",
      "info": "",
      "result": "Success",
      "time": "Saturday, 04-May-19 09:35:25 UTC"
    },
    {
      "build": "https://ci.chromium.org/b/8914400825743537840",
      "duration": "4 mins 5 secs",
      "info": "",
      "result": "Success",
      "time": "Saturday, 04-May-19 09:29:28 UTC"
    },
    {
      "build": "https://ci.chromium.org/b/8914401183298039312",
      "duration": "4 mins 7 secs",
      "info": "",
      "result": "Success",
      "time": "Saturday, 04-May-19 09:23:55 UTC"
    },
    {
      "build": "https://ci.chromium.org/b/8914401527311035536",
      "duration": "4 mins 11 secs",
      "info": "",
      "result": "Success",
      "time": "Saturday, 04-May-19 09:18:20 UTC"
    },
    {
      "build": "https://ci.chromium.org/b/8914401879212613744",
      "duration": "3 mins 59 secs",
      "info": "",
      "result": "Success",
      "time": "Saturday, 04-May-19 09:12:52 UTC"
    },
    {
      "build": "https://ci.chromium.org/b/8914402219293921344",
      "duration": "3 mins 59 secs",
      "info": "",
      "result": "Success",
      "time": "Saturday, 04-May-19 09:07:15 UTC"
    },
    {
      "build": "https://ci.chromium.org/b/8914402567175804512",
      "duration": "4 mins 5 secs",
      "info": "",
      "result": "Success",
      "time": "Saturday, 04-May-19 09:01:53 UTC"
    },
    {
      "build": "https://ci.chromium.org/b/8914402928139419824",
      "duration": "3 mins 59 secs",
      "info": "",
      "result": "Success",
      "time": "Saturday, 04-May-19 08:56:19 UTC"
    },
    {
      "build": "https://ci.chromium.org/b/8914403297112940080",
      "duration": "4 mins 15 secs",
      "info": "",
      "result": "Success",
      "time": "Saturday, 04-May-19 08:50:36 UTC"
    },
    {
      "build": "https://ci.chromium.org/b/8914403653920975088",
      "duration": "4 mins 2 secs",
      "info": "",
      "result": "Success",
      "time": "Saturday, 04-May-19 08:44:45 UTC"
    },
    {
      "build": "https://ci.chromium.org/b/8914404001747145552",
      "duration": "3 mins 57 secs",
      "info": "",
      "result": "Success",
      "time": "Saturday, 04-May-19 08:38:59 UTC"
    },
    {
      "build": "https://ci.chromium.org/b/8914404345424759392",
      "duration": "4 mins 3 secs",
      "info": "",
      "result": "Success",
      "time": "Saturday, 04-May-19 08:33:32 UTC"
    },
    {
      "build": "https://ci.chromium.org/b/8914404691862214720",
      "duration": "4 mins 2 secs",
      "info": "",
      "result": "Success",
      "time": "Saturday, 04-May-19 08:28:04 UTC"
    },
    {
      "build": "https://ci.chromium.org/b/8914405029306497872",
      "duration": "4 mins 4 secs",
      "info": "",
      "result": "Success",
      "time": "Saturday, 04-May-19 08:22:34 UTC"
    },
    {
      "build": "https://ci.chromium.org/b/8914405377890854576",
      "duration": "4 mins",
      "info": "",
      "result": "Success",
      "time": "Saturday, 04-May-19 08:17:11 UTC"
    },
    {
      "build": "https://ci.chromium.org/b/8914405735670477056",
      "duration": "4 mins 9 secs",
      "info": "",
      "result": "Success",
      "time": "Saturday, 04-May-19 08:11:39 UTC"
    },
    {
      "build": "https://ci.chromium.org/b/8914406103077202000",
      "duration": "4 mins 4 secs",
      "info": "",
      "result": "Success",
      "time": "Saturday, 04-May-19 08:05:57 UTC"
    },
    {
      "build": "https://ci.chromium.org/b/8914406442939091872",
      "duration": "3 mins 58 secs",
      "info": "",
      "result": "Success",
      "time": "Saturday, 04-May-19 08:00:08 UTC"
    },
    {
      "build": "https://ci.chromium.org/b/8914406778616107472",
      "duration": "3 mins 57 secs",
      "info": "",
      "result": "Success",
      "time": "Saturday, 04-May-19 07:54:46 UTC"
    },
    {
      "build": "https://ci.chromium.org/b/8914407109952468032",
      "duration": "3 mins 59 secs",
      "info": "",
      "result": "Success",
      "time": "Saturday, 04-May-19 07:49:24 UTC"
    },
    {
      "build": "https://ci.chromium.org/b/8914407435001119872",
      "duration": "3 mins 52 secs",
      "info": "",
      "result": "Success",
      "time": "Saturday, 04-May-19 07:44:08 UTC"
    },
    {
      "build": "https://ci.chromium.org/b/8914407764001936624",
      "duration": "3 mins 58 secs",
      "info": "",
      "result": "Success",
      "time": "Saturday, 04-May-19 07:38:59 UTC"
    },
    {
      "build": "https://ci.chromium.org/b/8914408118799108176",
      "duration": "4 mins 6 secs",
      "info": "",
      "result": "Success",
      "time": "Saturday, 04-May-19 07:33:44 UTC"
    },
    {
      "build": "https://ci.chromium.org/b/8914408489357718448",
      "duration": "4 mins 25 secs",
      "info": "",
      "result": "Success",
      "time": "Saturday, 04-May-19 07:28:04 UTC"
    },
    {
      "build": "https://ci.chromium.org/b/8914408841209240768",
      "duration": "4 mins",
      "info": "",
      "result": "Success",
      "time": "Saturday, 04-May-19 07:22:09 UTC"
    },
    {
      "build": "https://ci.chromium.org/b/8914409172961913632",
      "duration": "3 mins 55 secs",
      "info": "",
      "result": "Success",
      "time": "Saturday, 04-May-19 07:16:37 UTC"
    },
    {
      "build": "https://ci.chromium.org/b/8914409502958117872",
      "duration": "3 mins 59 secs",
      "info": "",
      "result": "Success",
      "time": "Saturday, 04-May-19 07:11:20 UTC"
    },
    {
      "build": "https://ci.chromium.org/b/8914409857169320256",
      "duration": "4 mins 5 secs",
      "info": "",
      "result": "Success",
      "time": "Saturday, 04-May-19 07:06:02 UTC"
    },
    {
      "build": "https://ci.chromium.org/b/8914410196524107936",
      "duration": "4 mins 2 secs",
      "info": "",
      "result": "Success",
      "time": "Saturday, 04-May-19 07:00:29 UTC"
    },
    {
      "build": "https://ci.chromium.org/b/8914410531649260784",
      "duration": "4 mins 1 secs",
      "info": "",
      "result": "Success",
      "time": "Saturday, 04-May-19 06:55:02 UTC"
    },
    {
      "build": "https://ci.chromium.org/b/8914410863826664528",
      "duration": "3 mins 59 secs",
      "info": "",
      "result": "Success",
      "time": "Saturday, 04-May-19 06:49:42 UTC"
    },
    {
      "build": "https://ci.chromium.org/b/8914411258052968768",
      "duration": "4 mins 33 secs",
      "info": "",
      "result": "Success",
      "time": "Saturday, 04-May-19 06:44:30 UTC"
    },
    {
      "build": "https://ci.chromium.org/b/8914411597862624064",
      "duration": "3 mins 59 secs",
      "info": "",
      "result": "Success",
      "time": "Saturday, 04-May-19 06:38:12 UTC"
    },
    {
      "build": "https://ci.chromium.org/b/8914411931448816592",
      "duration": "3 mins 59 secs",
      "info": "",
      "result": "Success",
      "time": "Saturday, 04-May-19 06:32:49 UTC"
    },
    {
      "build": "https://ci.chromium.org/b/8914412300523579440",
      "duration": "4 mins 33 secs",
      "info": "",
      "result": "Success",
      "time": "Saturday, 04-May-19 06:27:30 UTC"
    },
    {
      "build": "https://ci.chromium.org/b/8914412643994015104",
      "duration": "4 mins 9 secs",
      "info": "",
      "result": "Success",
      "time": "Saturday, 04-May-19 06:21:39 UTC"
    },
    {
      "build": "https://ci.chromium.org/b/8914413285489556624",
      "duration": "8 mins 33 secs",
      "info": "",
      "result": "Success",
      "time": "Saturday, 04-May-19 06:16:11 UTC"
    },
    {
      "build": "https://ci.chromium.org/b/8914413734555989088",
      "duration": "4 mins 2 secs",
      "info": "",
      "result": "Success",
      "time": "Saturday, 04-May-19 06:05:58 UTC"
    },
    {
      "build": "https://ci.chromium.org/b/8914414093277690672",
      "duration": "4 mins 32 secs",
      "info": "",
      "result": "Success",
      "time": "Saturday, 04-May-19 05:58:52 UTC"
    },
    {
      "build": "https://ci.chromium.org/b/8914414477292089376",
      "duration": "4 mins 46 secs",
      "info": "",
      "result": "Success",
      "time": "Saturday, 04-May-19 05:53:08 UTC"
    },
    {
      "build": "https://ci.chromium.org/b/8914414835970486816",
      "duration": "4 mins 19 secs",
      "info": "",
      "result": "Success",
      "time": "Saturday, 04-May-19 05:47:02 UTC"
    },
    {
      "build": "https://ci.chromium.org/b/8914415163172474160",
      "duration": "4 mins 4 secs",
      "info": "",
      "result": "Success",
      "time": "Saturday, 04-May-19 05:41:22 UTC"
    },
    {
      "build": "https://ci.chromium.org/b/8914415515412297296",
      "duration": "4 mins 11 secs",
      "info": "",
      "result": "Success",
      "time": "Saturday, 04-May-19 05:36:08 UTC"
    },
    {
      "build": "https://ci.chromium.org/b/8914415852502030896",
      "duration": "4 mins 4 secs",
      "info": "",
      "result": "Success",
      "time": "Saturday, 04-May-19 05:30:32 UTC"
    },
    {
      "build": "https://ci.chromium.org/b/8914416203165599248",
      "duration": "4 mins 8 secs",
      "info": "",
      "result": "Success",
      "time": "Saturday, 04-May-19 05:25:09 UTC"
    },
    {
      "build": "https://ci.chromium.org/b/8914416549060650544",
      "duration": "4 mins 5 secs",
      "info": "",
      "result": "Success",
      "time": "Saturday, 04-May-19 05:19:38 UTC"
    },
    {
      "build": "https://ci.chromium.org/b/8914416987470418912",
      "duration": "4 mins 23 secs",
      "info": "",
      "result": "Success",
      "time": "Saturday, 04-May-19 05:14:07 UTC"
    },
    {
      "build": "https://ci.chromium.org/b/8914417329291621712",
      "duration": "4 mins 3 secs",
      "info": "",
      "result": "Success",
      "time": "Saturday, 04-May-19 05:07:04 UTC"
    },
    {
      "build": "https://ci.chromium.org/b/8914417662724164000",
      "duration": "4 mins",
      "info": "",
      "result": "Success",
      "time": "Saturday, 04-May-19 05:01:42 UTC"
    },
    {
      "build": "https://ci.chromium.org/b/8914417998498696848",
      "duration": "4 mins 2 secs",
      "info": "",
      "result": "Success",
      "time": "Saturday, 04-May-19 04:56:24 UTC"
    },
    {
      "build": "https://ci.chromium.org/b/8914418358618678912",
      "duration": "4 mins 1 secs",
      "info": "",
      "result": "Success",
      "time": "Saturday, 04-May-19 04:51:05 UTC"
    },
    {
      "build": "https://ci.chromium.org/b/8914418694176924912",
      "duration": "4 mins 2 secs",
      "info": "",
      "result": "Success",
      "time": "Saturday, 04-May-19 04:45:21 UTC"
    },
    {
      "build": "https://ci.chromium.org/b/8914419049176156800",
      "duration": "4 mins 18 secs",
      "info": "",
      "result": "Success",
      "time": "Saturday, 04-May-19 04:40:01 UTC"
    },
    {
      "build": "https://ci.chromium.org/b/8914419380406466176",
      "duration": "4 mins 7 secs",
      "info": "",
      "result": "Success",
      "time": "Saturday, 04-May-19 04:34:25 UTC"
    },
    {
      "build": "https://ci.chromium.org/b/8914419728440261344",
      "duration": "4 mins 6 secs",
      "info": "",
      "result": "Success",
      "time": "Saturday, 04-May-19 04:29:06 UTC"
    },
    {
      "build": "https://ci.chromium.org/b/8914420076459678512",
      "duration": "4 mins 10 secs",
      "info": "",
      "result": "Success",
      "time": "Saturday, 04-May-19 04:23:34 UTC"
    },
    {
      "build": "https://ci.chromium.org/b/8914420418461706784",
      "duration": "4 mins 9 secs",
      "info": "",
      "result": "Success",
      "time": "Saturday, 04-May-19 04:18:04 UTC"
    },
    {
      "build": "https://ci.chromium.org/b/8914420753870220016",
      "duration": "4 mins 7 secs",
      "info": "",
      "result": "Success",
      "time": "Saturday, 04-May-19 04:12:37 UTC"
    },
    {
      "build": "https://ci.chromium.org/b/8914421093411485952",
      "duration": "4 mins 1 secs",
      "info": "",
      "result": "Success",
      "time": "Saturday, 04-May-19 04:07:17 UTC"
    },
    {
      "build": "https://ci.chromium.org/b/8914421444083551648",
      "duration": "4 mins 13 secs",
      "info": "",
      "result": "Success",
      "time": "Saturday, 04-May-19 04:01:52 UTC"
    },
    {
      "build": "https://ci.chromium.org/b/8914421787311933504",
      "duration": "4 mins 8 secs",
      "info": "",
      "result": "Success",
      "time": "Saturday, 04-May-19 03:56:20 UTC"
    },
    {
      "build": "https://ci.chromium.org/b/8914422136198164992",
      "duration": "4 mins 11 secs",
      "info": "",
      "result": "Success",
      "time": "Saturday, 04-May-19 03:50:52 UTC"
    },
    {
      "build": "https://ci.chromium.org/b/8914422492172250752",
      "duration": "4 mins 9 secs",
      "info": "",
      "result": "Success",
      "time": "Saturday, 04-May-19 03:45:21 UTC"
    },
    {
      "build": "https://ci.chromium.org/b/8914422851274373984",
      "duration": "4 mins 20 secs",
      "info": "",
      "result": "Success",
      "time": "Saturday, 04-May-19 03:39:39 UTC"
    },
    {
      "build": "https://ci.chromium.org/b/8914423209907991888",
      "duration": "4 mins 23 secs",
      "info": "",
      "result": "Success",
      "time": "Saturday, 04-May-19 03:33:58 UTC"
    },
    {
      "build": "https://ci.chromium.org/b/8914423630990322352",
      "duration": "4 mins 5 secs",
      "info": "",
      "result": "Success",
      "time": "Saturday, 04-May-19 03:28:15 UTC"
    },
    {
      "build": "https://ci.chromium.org/b/8914423983190914256",
      "duration": "4 mins 15 secs",
      "info": "",
      "result": "Success",
      "time": "Saturday, 04-May-19 03:21:33 UTC"
    },
    {
      "build": "https://ci.chromium.org/b/8914424321025853328",
      "duration": "4 mins 1 secs",
      "info": "",
      "result": "Success",
      "time": "Saturday, 04-May-19 03:15:58 UTC"
    },
    {
      "build": "https://ci.chromium.org/b/8914424663215482896",
      "duration": "4 mins 3 secs",
      "info": "",
      "result": "Success",
      "time": "Saturday, 04-May-19 03:10:35 UTC"
    },
    {
      "build": "https://ci.chromium.org/b/8914425009193197936",
      "duration": "4 mins 9 secs",
      "info": "",
      "result": "Success",
      "time": "Saturday, 04-May-19 03:05:08 UTC"
    },
    {
      "build": "https://ci.chromium.org/b/8914425351103771968",
      "duration": "4 mins 3 secs",
      "info": "",
      "result": "Success",
      "time": "Saturday, 04-May-19 02:59:38 UTC"
    },
    {
      "build": "https://ci.chromium.org/b/8914425715889523680",
      "duration": "4 mins 6 secs",
      "info": "",
      "result": "Success",
      "time": "Saturday, 04-May-19 02:54:13 UTC"
    },
    {
      "build": "https://ci.chromium.org/b/8914426052987479824",
      "duration": "4 mins 3 secs",
      "info": "",
      "result": "Success",
      "time": "Saturday, 04-May-19 02:48:25 UTC"
    },
    {
      "build": "https://ci.chromium.org/b/8914426395508244400",
      "duration": "4 mins",
      "info": "",
      "result": "Success",
      "time": "Saturday, 04-May-19 02:43:04 UTC"
    },
    {
      "build": "https://ci.chromium.org/b/8914426741493061312",
      "duration": "4 mins 7 secs",
      "info": "",
      "result": "Success",
      "time": "Saturday, 04-May-19 02:37:38 UTC"
    },
    {
      "build": "https://ci.chromium.org/b/8914427089294230064",
      "duration": "4 mins 9 secs",
      "info": "",
      "result": "Success",
      "time": "Saturday, 04-May-19 02:32:05 UTC"
    },
    {
      "build": "https://ci.chromium.org/b/8914427468338138672",
      "duration": "4 mins 39 secs",
      "info": "",
      "result": "Success",
      "time": "Saturday, 04-May-19 02:26:35 UTC"
    },
    {
      "build": "https://ci.chromium.org/b/8914427833897955728",
      "duration": "4 mins 30 secs",
      "info": "",
      "result": "Success",
      "time": "Saturday, 04-May-19 02:20:32 UTC"
    },
    {
      "build": "https://ci.chromium.org/b/8914428178060680336",
      "duration": "4 mins 7 secs",
      "info": "",
      "result": "Success",
      "time": "Saturday, 04-May-19 02:14:44 UTC"
    },
    {
      "build": "https://ci.chromium.org/b/8914428544720380592",
      "duration": "4 mins 7 secs",
      "info": "",
      "result": "Success",
      "time": "Saturday, 04-May-19 02:09:17 UTC"
    },
    {
      "build": "https://ci.chromium.org/b/8914428916302017584",
      "duration": "4 mins 34 secs",
      "info": "",
      "result": "Success",
      "time": "Saturday, 04-May-19 02:03:28 UTC"
    },
    {
      "build": "https://ci.chromium.org/b/8914429282330879216",
      "duration": "4 mins 30 secs",
      "info": "",
      "result": "Success",
      "time": "Saturday, 04-May-19 01:57:32 UTC"
    },
    {
      "build": "https://ci.chromium.org/b/8914429633540200528",
      "duration": "4 mins 8 secs",
      "info": "",
      "result": "Success",
      "time": "Saturday, 04-May-19 01:51:43 UTC"
    },
    {
      "build": "https://ci.chromium.org/b/8914429970384470336",
      "duration": "4 mins 4 secs",
      "info": "",
      "result": "Success",
      "time": "Saturday, 04-May-19 01:46:08 UTC"
    },
    {
      "build": "https://ci.chromium.org/b/8914430323215711072",
      "duration": "4 mins 8 secs",
      "info": "",
      "result": "Success",
      "time": "Saturday, 04-May-19 01:40:44 UTC"
    },
    {
      "build": "https://ci.chromium.org/b/8914430675654893696",
      "duration": "4 mins 13 secs",
      "info": "",
      "result": "Success",
      "time": "Saturday, 04-May-19 01:35:11 UTC"
    },
    {
      "build": "https://ci.chromium.org/b/8914431036288589728",
      "duration": "4 mins 10 secs",
      "info": "",
      "result": "Success",
      "time": "Saturday, 04-May-19 01:29:33 UTC"
    },
    {
      "build": "https://ci.chromium.org/b/8914431397091983136",
      "duration": "4 mins 8 secs",
      "info": "",
      "result": "Success",
      "time": "Saturday, 04-May-19 01:23:47 UTC"
    },
    {
      "build": "https://ci.chromium.org/b/8914431774483223808",
      "duration": "4 mins 12 secs",
      "info": "",
      "result": "Success",
      "time": "Saturday, 04-May-19 01:18:06 UTC"
    },
    {
      "build": "https://ci.chromium.org/b/8914432160263890192",
      "duration": "4 mins 38 secs",
      "info": "",
      "result": "Success",
      "time": "Saturday, 04-May-19 01:12:06 UTC"
    },
    {
      "build": "https://ci.chromium.org/b/8914432524816779264",
      "duration": "4 mins 20 secs",
      "info": "",
      "result": "Success",
      "time": "Saturday, 04-May-19 01:05:57 UTC"
    },
    {
      "build": "https://ci.chromium.org/b/8914432882056199696",
      "duration": "4 mins 6 secs",
      "info": "",
      "result": "Success",
      "time": "Saturday, 04-May-19 01:00:10 UTC"
    },
    {
      "build": "https://ci.chromium.org/b/8914433301310067008",
      "duration": "4 mins 53 secs",
      "info": "",
      "result": "Success",
      "time": "Saturday, 04-May-19 00:54:30 UTC"
    },
    {
      "build": "https://ci.chromium.org/b/8914433657901373984",
      "duration": "4 mins 20 secs",
      "info": "",
      "result": "Success",
      "time": "Saturday, 04-May-19 00:47:46 UTC"
    },
    {
      "build": "https://ci.chromium.org/b/8914434048467645600",
      "duration": "4 mins 14 secs",
      "info": "",
      "result": "Success",
      "time": "Saturday, 04-May-19 00:42:07 UTC"
    },
    {
      "build": "https://ci.chromium.org/b/8914434401970569536",
      "duration": "4 mins 16 secs",
      "info": "",
      "result": "Success",
      "time": "Saturday, 04-May-19 00:35:56 UTC"
    },
    {
      "build": "https://ci.chromium.org/b/8914434737764862736",
      "duration": "4 mins 9 secs",
      "info": "",
      "result": "Success",
      "time": "Saturday, 04-May-19 00:30:20 UTC"
    },
    {
      "build": "https://ci.chromium.org/b/8914435096421114608",
      "duration": "4 mins 18 secs",
      "info": "",
      "result": "Success",
      "time": "Saturday, 04-May-19 00:25:01 UTC"
    },
    {
      "build": "https://ci.chromium.org/b/8914435477487412992",
      "duration": "4 mins 38 secs",
      "info": "",
      "result": "Success",
      "time": "Saturday, 04-May-19 00:19:20 UTC"
    },
    {
      "build": "https://ci.chromium.org/b/8914435886656243744",
      "duration": "4 mins 19 secs",
      "info": "",
      "result": "Success",
      "time": "Saturday, 04-May-19 00:13:13 UTC"
    },
    {
      "build": "https://ci.chromium.org/b/8914436551741025264",
      "duration": "4 mins 13 secs",
      "info": "",
      "result": "Success",
      "time": "Saturday, 04-May-19 00:01:42 UTC"
    },
    {
      "build": "https://ci.chromium.org/b/8914436893876783200",
      "duration": "4 mins 7 secs",
      "info": "",
      "result": "Success",
      "time": "Friday, 03-May-19 23:56:11 UTC"
    },
    {
      "build": "https://ci.chromium.org/b/8914437233989398624",
      "duration": "4 mins 8 secs",
      "info": "",
      "result": "Success",
      "time": "Friday, 03-May-19 23:50:46 UTC"
    },
    {
      "build": "https://ci.chromium.org/b/8914437569071142624",
      "duration": "4 mins",
      "info": "",
      "result": "Success",
      "time": "Friday, 03-May-19 23:45:19 UTC"
    },
    {
      "build": "https://ci.chromium.org/b/8914437910315685952",
      "duration": "4 mins 5 secs",
      "info": "",
      "result": "Success",
      "time": "Friday, 03-May-19 23:40:01 UTC"
    },
    {
      "build": "https://ci.chromium.org/b/8914438254918307728",
      "duration": "4 mins 11 secs",
      "info": "",
      "result": "Success",
      "time": "Friday, 03-May-19 23:34:36 UTC"
    },
    {
      "build": "https://ci.chromium.org/b/8914438598353593104",
      "duration": "4 mins 5 secs",
      "info": "",
      "result": "Success",
      "time": "Friday, 03-May-19 23:29:06 UTC"
    },
    {
      "build": "https://ci.chromium.org/b/8914438940670432000",
      "duration": "4 mins 8 secs",
      "info": "",
      "result": "Success",
      "time": "Friday, 03-May-19 23:23:40 UTC"
    },
    {
      "build": "https://ci.chromium.org/b/8914439294722999616",
      "duration": "4 mins 17 secs",
      "info": "",
      "result": "Success",
      "time": "Friday, 03-May-19 23:18:12 UTC"
    },
    {
      "build": "https://ci.chromium.org/b/8914439653414959072",
      "duration": "4 mins 16 secs",
      "info": "",
      "result": "Success",
      "time": "Friday, 03-May-19 23:12:35 UTC"
    },
    {
      "build": "https://ci.chromium.org/b/8914440026776785584",
      "duration": "4 mins 15 secs",
      "info": "",
      "result": "Success",
      "time": "Friday, 03-May-19 23:06:54 UTC"
    },
    {
      "build": "https://ci.chromium.org/b/8914440368713080960",
      "duration": "4 mins 6 secs",
      "info": "",
      "result": "Success",
      "time": "Friday, 03-May-19 23:00:58 UTC"
    },
    {
      "build": "https://ci.chromium.org/b/8914440711458178192",
      "duration": "4 mins 6 secs",
      "info": "",
      "result": "Success",
      "time": "Friday, 03-May-19 22:55:31 UTC"
    },
    {
      "build": "https://ci.chromium.org/b/8914441060583824032",
      "duration": "4 mins 12 secs",
      "info": "",
      "result": "Success",
      "time": "Friday, 03-May-19 22:50:02 UTC"
    },
    {
      "build": "https://ci.chromium.org/b/8914441406814102032",
      "duration": "4 mins 13 secs",
      "info": "",
      "result": "Success",
      "time": "Friday, 03-May-19 22:44:31 UTC"
    },
    {
      "build": "https://ci.chromium.org/b/8914441755087815568",
      "duration": "4 mins 13 secs",
      "info": "",
      "result": "Success",
      "time": "Friday, 03-May-19 22:39:00 UTC"
    },
    {
      "build": "https://ci.chromium.org/b/8914442105105928464",
      "duration": "4 mins 16 secs",
      "info": "",
      "result": "Success",
      "time": "Friday, 03-May-19 22:33:29 UTC"
    },
    {
      "build": "https://ci.chromium.org/b/8914442449149190192",
      "duration": "4 mins 15 secs",
      "info": "",
      "result": "Success",
      "time": "Friday, 03-May-19 22:27:55 UTC"
    },
    {
      "build": "https://ci.chromium.org/b/8914442828643938272",
      "duration": "4 mins 40 secs",
      "info": "",
      "result": "Success",
      "time": "Friday, 03-May-19 22:22:26 UTC"
    },
    {
      "build": "https://ci.chromium.org/b/8914443174623895760",
      "duration": "4 mins 13 secs",
      "info": "",
      "result": "Success",
      "time": "Friday, 03-May-19 22:16:25 UTC"
    },
    {
      "build": "https://ci.chromium.org/b/8914443520062727872",
      "duration": "4 mins 12 secs",
      "info": "",
      "result": "Success",
      "time": "Friday, 03-May-19 22:10:55 UTC"
    },
    {
      "build": "https://ci.chromium.org/b/8914443863956921760",
      "duration": "4 mins 9 secs",
      "info": "",
      "result": "Success",
      "time": "Friday, 03-May-19 22:05:25 UTC"
    },
    {
      "build": "https://ci.chromium.org/b/8914444210736945184",
      "duration": "4 mins 10 secs",
      "info": "",
      "result": "Success",
      "time": "Friday, 03-May-19 21:59:57 UTC"
    },
    {
      "build": "https://ci.chromium.org/b/8914444554593601152",
      "duration": "4 mins 11 secs",
      "info": "",
      "result": "Success",
      "time": "Friday, 03-May-19 21:54:28 UTC"
    },
    {
      "build": "https://ci.chromium.org/b/8914444908749770064",
      "duration": "4 mins 16 secs",
      "info": "",
      "result": "Success",
      "time": "Friday, 03-May-19 21:48:55 UTC"
    }
  ],
  "last_success": "Saturday, 04-May-19 16:30:34 UTC",
  "recent_failures": 0
}